toc/__init__.py
toc/cli.py
toc/toc.py
tableofcontents-2.7.3.dist-info/LICENSE
tableofcontents-2.7.3.dist-info/METADATA
tableofcontents-2.7.3.dist-info/WHEEL
tableofcontents-2.7.3.dist-info/entry_points.txt
tableofcontents-2.7.3.dist-info/top_level.txt
tableofcontents-2.7.3.dist-info/RECORD
