Metadata-Version: 2.1
Name: tableofcontents
Version: 2.7.3
Summary: Generate a table of contents from the comments of a file
Author: AlphaJack
Project-URL: Homepage, https://github.com/AlphaJack/toc
Project-URL: Issues, https://github.com/AlphaJack/toc/issues
Project-URL: Repository, https://github.com/AlphaJack/toc
Project-URL: Changelog, https://github.com/AlphaJack/toc/blob/master/CHANGELOG.md
Classifier: Development Status :: 5 - Production/Stable
Classifier: Intended Audience :: Developers
Classifier: Topic :: Software Development :: Documentation
Classifier: Topic :: Text Processing
Classifier: Topic :: Utilities
Classifier: Environment :: Console
Classifier: License :: OSI Approved :: GNU General Public License v3 (GPLv3)
Classifier: Operating System :: OS Independent
Classifier: Programming Language :: Python :: 3
Requires-Python: >=3.10
License-File: LICENSE
Requires-Dist: importlib-metadata
